brand_yml/__init__.py
brand_yml/__version.py
brand_yml/_defs.py
brand_yml/_utils.py
brand_yml/_utils_docs.py
brand_yml/_utils_logging.py
brand_yml/_utils_yaml.py
brand_yml/base.py
brand_yml/color.py
brand_yml/file.py
brand_yml/logo.py
brand_yml/meta.py
brand_yml/py.typed
brand_yml/typography.py
brand_yml/examples/brand-color-direct-posit.yml
brand_yml/examples/brand-color-palette-internal.yml
brand_yml/examples/brand-color-palette-posit.yml
brand_yml/examples/brand-logo-full-alt.yml
brand_yml/examples/brand-logo-full.yml
brand_yml/examples/brand-logo-light-dark.yml
brand_yml/examples/brand-logo-simple.yml
brand_yml/examples/brand-logo-single.yml
brand_yml/examples/brand-meta-full.yml
brand_yml/examples/brand-meta-small.yml
brand_yml/examples/brand-posit.yml
brand_yml/examples/brand-typography-color.yml
brand_yml/examples/brand-typography-fonts.yml
brand_yml/examples/brand-typography-minimal-system.yml
brand_yml/examples/brand-typography-minimal.yml
brand_yml/examples/brand-typography-simple.yml
brand_yml/examples/fonts/open-sans/OpenSans-Variable-Italic.ttf
brand_yml/examples/fonts/open-sans/OpenSans-Variable.ttf
brand_yml/examples/logos/pandas/pandas.svg
brand_yml/examples/logos/pandas/pandas_mark.svg
brand_yml/examples/logos/pandas/pandas_mark_white.svg
brand_yml/examples/logos/pandas/pandas_secondary.svg
brand_yml/examples/logos/pandas/pandas_secondary_white.svg
brand_yml/examples/logos/pandas/pandas_white.svg
brand_yml-0.1.0.dist-info/METADATA
brand_yml-0.1.0.dist-info/WHEEL
brand_yml-0.1.0.dist-info/licenses/LICENSE.md
brand_yml-0.1.0.dist-info/RECORD
